odoo10_addon_hr_holidays_imposed_days-10.0.1.0.1-nspkg.pth
odoo/addons/hr_holidays_imposed_days/README.rst
odoo/addons/hr_holidays_imposed_days/__init__.py
odoo/addons/hr_holidays_imposed_days/__manifest__.py
odoo/addons/hr_holidays_imposed_days/i18n/ar.po
odoo/addons/hr_holidays_imposed_days/i18n/cs_CZ.po
odoo/addons/hr_holidays_imposed_days/i18n/de.po
odoo/addons/hr_holidays_imposed_days/i18n/es.po
odoo/addons/hr_holidays_imposed_days/i18n/fi.po
odoo/addons/hr_holidays_imposed_days/i18n/fr.po
odoo/addons/hr_holidays_imposed_days/i18n/hr.po
odoo/addons/hr_holidays_imposed_days/i18n/hr_HR.po
odoo/addons/hr_holidays_imposed_days/i18n/hr_holidays_imposed_days.pot
odoo/addons/hr_holidays_imposed_days/i18n/it.po
odoo/addons/hr_holidays_imposed_days/i18n/lt.po
odoo/addons/hr_holidays_imposed_days/i18n/nl_NL.po
odoo/addons/hr_holidays_imposed_days/i18n/pl.po
odoo/addons/hr_holidays_imposed_days/i18n/pt_BR.po
odoo/addons/hr_holidays_imposed_days/i18n/ro.po
odoo/addons/hr_holidays_imposed_days/i18n/sl.po
odoo/addons/hr_holidays_imposed_days/models/__init__.py
odoo/addons/hr_holidays_imposed_days/models/hr_employee.py
odoo/addons/hr_holidays_imposed_days/models/hr_imposed_holidays.py
odoo/addons/hr_holidays_imposed_days/security/ir.model.access.csv
odoo/addons/hr_holidays_imposed_days/static/description/icon.png
odoo/addons/hr_holidays_imposed_days/tests/__init__.py
odoo/addons/hr_holidays_imposed_days/tests/test_holidays_imposed_days.py
odoo/addons/hr_holidays_imposed_days/views/imposed_days.xml
odoo10_addon_hr_holidays_imposed_days-10.0.1.0.1.dist-info/METADATA
odoo10_addon_hr_holidays_imposed_days-10.0.1.0.1.dist-info/WHEEL
odoo10_addon_hr_holidays_imposed_days-10.0.1.0.1.dist-info/namespace_packages.txt
odoo10_addon_hr_holidays_imposed_days-10.0.1.0.1.dist-info/top_level.txt
odoo10_addon_hr_holidays_imposed_days-10.0.1.0.1.dist-info/RECORD
